apkcli/__init__.py
apkcli/main.py
apkcli/data/trusted_certs.csv
apkcli/lib/utils.py
apkcli/plugins/arsc.py
apkcli/plugins/base.py
apkcli/plugins/cert.py
apkcli/plugins/check.py
apkcli/plugins/dex.py
apkcli/plugins/enump.py
apkcli/plugins/find.py
apkcli/plugins/frosting.py
apkcli/plugins/info.py
apkcli/plugins/jsonp.py
apkcli/plugins/manifest.py
apkcli/plugins/permissions.py
apkcli/plugins/shell.py
apkcli/plugins/strings.py
apkcli/plugins/urls.py
apkcli/plugins/yarap.py
apkcli-0.1.3.dist-info/LICENSE
apkcli-0.1.3.dist-info/METADATA
apkcli-0.1.3.dist-info/WHEEL
apkcli-0.1.3.dist-info/entry_points.txt
apkcli-0.1.3.dist-info/top_level.txt
apkcli-0.1.3.dist-info/RECORD
