Metadata-Version: 2.1
Name: apkcli
Version: 0.1.3
Summary: Another APK info tool
Home-page: https://github.com/Te-k/apkcli
Author: Tek
Author-email: tek@randhome.io
License: MIT
Keywords: malware
Platform: UNKNOWN
Classifier: Programming Language :: Python :: 3
Classifier: License :: OSI Approved :: MIT License
Classifier: Operating System :: OS Independent
Requires-Python: >=3.5
License-File: LICENSE
Requires-Dist: androguard (==3.3.5)
Requires-Dist: ipython
Requires-Dist: yara-python (==4.1.0)
Requires-Dist: lxml (>=4.2.6)
